pydowndoc/__init__.py
pydowndoc/_utils.py
pydowndoc/conversion_backends.py
pydowndoc/hatch_hooks.py
pydowndoc/py.typed
pydowndoc-2.1.8.dist-info/METADATA
pydowndoc-2.1.8.dist-info/WHEEL
pydowndoc-2.1.8.dist-info/entry_points.txt
pydowndoc-2.1.8.dist-info/licenses/LICENSE
pydowndoc-2.1.8.dist-info/RECORD
