Metadata-Version: 2.4
Name: Pydowndoc
Version: 2.1.8
Summary: Python wrapper for converting/reducing AsciiDoc files back to Markdown.
Project-URL: Issues, https://github.com/CarrotManMatt/Pydowndoc/issues
Project-URL: Releases, https://github.com/CarrotManMatt/Pydowndoc/releases
Project-URL: Repository, https://github.com/CarrotManMatt/Pydowndoc
Author-email: Matt Norton <matt@carrotmanmatt.com>
License-Expression: Apache-2.0
License-File: LICENSE
Keywords: AsciiDoc,Hatch,Hatchling,Markdown,Python,README,build,converter,documentation,metadata,packaging,pypi,pyproject.toml
Classifier: Development Status :: 5 - Production/Stable
Classifier: Environment :: Console
Classifier: Framework :: Hatch
Classifier: Intended Audience :: Developers
Classifier: Operating System :: MacOS
Classifier: Operating System :: Microsoft :: Windows
Classifier: Operating System :: POSIX :: Linux
Classifier: Programming Language :: Python :: 3 :: Only
Classifier: Programming Language :: Python :: 3.9
Classifier: Programming Language :: Python :: 3.10
Classifier: Programming Language :: Python :: 3.11
Classifier: Programming Language :: Python :: 3.12
Classifier: Programming Language :: Python :: 3.13
Classifier: Programming Language :: Python :: 3.14
Classifier: Programming Language :: Python :: 3.15
Classifier: Topic :: Software Development
Classifier: Topic :: Text Processing :: Markup
Classifier: Typing :: Typed
Requires-Python: >=3.9
Requires-Dist: hatchling
Requires-Dist: typed-classproperties>=1.3
Requires-Dist: typing-extensions; python_version < '3.12'
Provides-Extra: bin
Requires-Dist: pydowndoc-bin; extra == 'bin'
